alps_unified_ts/__init__.py
alps_unified_ts/py.typed
alps_unified_ts/_jsii/__init__.py
alps_unified_ts/_jsii/alps-unified-ts@0.0.40.jsii.tgz
alps_unified_ts-0.0.40.dist-info/METADATA
alps_unified_ts-0.0.40.dist-info/WHEEL
alps_unified_ts-0.0.40.dist-info/top_level.txt
alps_unified_ts-0.0.40.dist-info/RECORD
